Metadata-Version: 1.1
Name: iddmma-tools
Version: 1.0
Summary: A Network Scan & Attack Tools
Home-page: https://github.com/pypa/sampleproject
Author: @ $#
Author-email: iddmma.manager@gmail.com
License: MIT
Keywords: Network Sniff & Monitoring Tools
Platform: UNKNOWN
Classifier: Development Status :: 3 - Alpha
Classifier: Intended Audience :: Developers
Classifier: Topic :: Software Development :: Build Tools
Classifier: License :: OSI Approved :: MIT License
Classifier: Programming Language :: Python :: 2
Classifier: Programming Language :: Python :: 2.7
Classifier: Programming Language :: Python :: 3
Classifier: Programming Language :: Python :: 3.3
Classifier: Programming Language :: Python :: 3.4
Classifier: Programming Language :: Python :: 3.5
